datamodule/__init__.py
datamodule/data_model.py
datamodule/log.py
datamodule/process_model.py
datamodule/utils.py
datamodule-0.1.post0.dist-info/DESCRIPTION.rst
datamodule-0.1.post0.dist-info/METADATA
datamodule-0.1.post0.dist-info/RECORD
datamodule-0.1.post0.dist-info/WHEEL
datamodule-0.1.post0.dist-info/metadata.json
datamodule-0.1.post0.dist-info/top_level.txt
